LICENSE
MANIFEST.in
README.rst
setup.cfg
setup.py
versioneer.py
artellapipe/__init__.py
artellapipe/libs/__init__.py
artellapipe/libs/arnold/__init__.py
artellapipe/libs/arnold/__logging__.ini
artellapipe/libs/arnold/__version__.py
artellapipe/libs/arnold/_version.py
artellapipe/libs/arnold/core/__init__.py
artellapipe/libs/arnold/core/arnold.py
artellapipe/libs/arnold/houdini/__init__.py
artellapipe/libs/arnold/maya/__init__.py
artellapipe/libs/arnold/maya/arnold.py
artellapipe_libs_arnold.egg-info/PKG-INFO
artellapipe_libs_arnold.egg-info/SOURCES.txt
artellapipe_libs_arnold.egg-info/dependency_links.txt
artellapipe_libs_arnold.egg-info/not-zip-safe
artellapipe_libs_arnold.egg-info/requires.txt
artellapipe_libs_arnold.egg-info/top_level.txt
tests/__init__.py
tests/test_general.py