Metadata-Version: 2.1
Name: artellapipe-libs-arnold
Version: 0.0.5
Summary: Library to manage Arnold data
Home-page: https://github.com/ArtellaPipe/artellapipe-libs-arnold
Author: Tomas Poveda
Author-email: tpovedatd@gmail.com
License: MIT
Platform: UNKNOWN
Provides-Extra: dev
Provides-Extra: test
